[{"__symbolic":"module","version":3,"metadata":{"LineCompareComponent":{"__symbolic":"class","decorators":[{"__symbolic":"call","expression":{"__symbolic":"reference","module":"@angular/core","name":"Component"},"arguments":[{"selector":"dmp-line-compare","styles":["\n    div.dmp-line-compare {\n      display: flex;\n      flex-direction: row;\n      border: 1px solid #808080;\n      font-family: Consolas, Courier, monospace;\n      width: 911px;\n    }\n    div.dmp-line-compare-margin {\n      width: 101px;\n    }\n    div.dmp-line-compare-content {\n      position: relative;\n      top: 0px;\n      left: 0px;\n      flex-grow: 1;\n      overflow-x: scroll;\n    }\n    div.dmp-line-compare-content-wrapper {\n      position: absolute;\n      top: 0px;\n      left: 0px;\n      display: flex;\n      flex-direction: column;\n      align-items: stretch;\n    }\n    div.dmp-line-compare-left {\n      width: 50px;\n      text-align: center;\n      color: #484848;\n    }\n    div.dmp-line-compare-equal>div.dmp-line-compare-left,\n      div.dmp-line-compare-equal>div.dmp-line-compare-right {\n      background-color: #dedede;\n    }\n    div.dmp-line-compare-insert>div.dmp-line-compare-left,\n      div.dmp-line-compare-insert>div.dmp-line-compare-right {\n      background-color: #8bfb6f;\n    }\n    div.dmp-line-compare-delete>div.dmp-line-compare-left,\n      div.dmp-line-compare-delete>div.dmp-line-compare-right {\n      background-color: #f56868;\n    }\n    div.dmp-line-compare-right {\n      width: 50px;\n      text-align: center;\n      color: #484848;\n      border-right: 1px solid #888888;\n    }\n    div.dmp-line-compare-text {\n      white-space: pre;\n      padding-left: 10px;\n      min-width: 800px;\n    }\n    .dmp-line-compare-delete {\n      background-color: #ff8c8c;\n    }\n    .dmp-line-compare-insert {\n      background-color: #9dff97;\n    }\n    .dmp-line-compare-delete>div {\n      display: inline-block;\n    }  \n    .dmp-line-compare-insert>div {\n      display: inline-block;\n    }\n    .dmp-line-compare-equal>div {\n      display: inline-block;\n    }\n    .dmp-margin-bottom-spacer {\n      height: 20px;\n      background-color: #dedede;\n      border-right: 1px solid #888888;\n    }\n  "],"template":"\n    <div class=\"dmp-line-compare-no-changes-text\" *ngIf=\"isContentEqual\">\n      There are no changes to display.\n    </div>    \n    <div class=\"dmp-line-compare\" *ngIf=\"!isContentEqual\">\n      <div class=\"dmp-line-compare-margin\">\n        <div [ngClass]=\"lineDiff[0]\" *ngFor=\"let lineDiff of calculatedDiff\">\n          <div class=\"dmp-line-compare-left\">{{lineDiff[1]}}</div><!-- No space\n        --><div class=\"dmp-line-compare-right\">{{lineDiff[2]}}</div>\n        </div>\n        <div class=\"dmp-margin-bottom-spacer\"></div>\n      </div><!-- No space\n   --><div class=\"dmp-line-compare-content\">\n        <div class=\"dmp-line-compare-content-wrapper\">\n          <div [ngClass]=\"lineDiff[0]\" *ngFor=\"let lineDiff of calculatedDiff\">\n            <div class=\"dmp-line-compare-text\">{{lineDiff[3]}}</div>\n          </div>\n        </div>\n      </div>\n    </div>\n  "}]}],"members":{"left":[{"__symbolic":"property","decorators":[{"__symbolic":"call","expression":{"__symbolic":"reference","module":"@angular/core","name":"Input"}}]}],"right":[{"__symbolic":"property","decorators":[{"__symbolic":"call","expression":{"__symbolic":"reference","module":"@angular/core","name":"Input"}}]}],"lineContextSize":[{"__symbolic":"property","decorators":[{"__symbolic":"call","expression":{"__symbolic":"reference","module":"@angular/core","name":"Input"}}]}],"__ctor__":[{"__symbolic":"constructor","parameters":[{"__symbolic":"reference","module":"./diffMatchPatch.service","name":"DiffMatchPatchService"}]}],"ngOnInit":[{"__symbolic":"method"}],"ngOnChanges":[{"__symbolic":"method"}],"updateHtml":[{"__symbolic":"method"}],"calculateLineDiff":[{"__symbolic":"method"}],"outputEqualDiff":[{"__symbolic":"method"}],"outputEqualDiffLines":[{"__symbolic":"method"}],"outputDeleteDiff":[{"__symbolic":"method"}],"outputInsertDiff":[{"__symbolic":"method"}]}}}},{"__symbolic":"module","version":1,"metadata":{"LineCompareComponent":{"__symbolic":"class","decorators":[{"__symbolic":"call","expression":{"__symbolic":"reference","module":"@angular/core","name":"Component"},"arguments":[{"selector":"dmp-line-compare","styles":["\n    div.dmp-line-compare {\n      display: flex;\n      flex-direction: row;\n      border: 1px solid #808080;\n      font-family: Consolas, Courier, monospace;\n      width: 911px;\n    }\n    div.dmp-line-compare-margin {\n      width: 101px;\n    }\n    div.dmp-line-compare-content {\n      position: relative;\n      top: 0px;\n      left: 0px;\n      flex-grow: 1;\n      overflow-x: scroll;\n    }\n    div.dmp-line-compare-content-wrapper {\n      position: absolute;\n      top: 0px;\n      left: 0px;\n      display: flex;\n      flex-direction: column;\n      align-items: stretch;\n    }\n    div.dmp-line-compare-left {\n      width: 50px;\n      text-align: center;\n      color: #484848;\n    }\n    div.dmp-line-compare-equal>div.dmp-line-compare-left,\n      div.dmp-line-compare-equal>div.dmp-line-compare-right {\n      background-color: #dedede;\n    }\n    div.dmp-line-compare-insert>div.dmp-line-compare-left,\n      div.dmp-line-compare-insert>div.dmp-line-compare-right {\n      background-color: #8bfb6f;\n    }\n    div.dmp-line-compare-delete>div.dmp-line-compare-left,\n      div.dmp-line-compare-delete>div.dmp-line-compare-right {\n      background-color: #f56868;\n    }\n    div.dmp-line-compare-right {\n      width: 50px;\n      text-align: center;\n      color: #484848;\n      border-right: 1px solid #888888;\n    }\n    div.dmp-line-compare-text {\n      white-space: pre;\n      padding-left: 10px;\n      min-width: 800px;\n    }\n    .dmp-line-compare-delete {\n      background-color: #ff8c8c;\n    }\n    .dmp-line-compare-insert {\n      background-color: #9dff97;\n    }\n    .dmp-line-compare-delete>div {\n      display: inline-block;\n    }  \n    .dmp-line-compare-insert>div {\n      display: inline-block;\n    }\n    .dmp-line-compare-equal>div {\n      display: inline-block;\n    }\n    .dmp-margin-bottom-spacer {\n      height: 20px;\n      background-color: #dedede;\n      border-right: 1px solid #888888;\n    }\n  "],"template":"\n    <div class=\"dmp-line-compare-no-changes-text\" *ngIf=\"isContentEqual\">\n      There are no changes to display.\n    </div>    \n    <div class=\"dmp-line-compare\" *ngIf=\"!isContentEqual\">\n      <div class=\"dmp-line-compare-margin\">\n        <div [ngClass]=\"lineDiff[0]\" *ngFor=\"let lineDiff of calculatedDiff\">\n          <div class=\"dmp-line-compare-left\">{{lineDiff[1]}}</div><!-- No space\n        --><div class=\"dmp-line-compare-right\">{{lineDiff[2]}}</div>\n        </div>\n        <div class=\"dmp-margin-bottom-spacer\"></div>\n      </div><!-- No space\n   --><div class=\"dmp-line-compare-content\">\n        <div class=\"dmp-line-compare-content-wrapper\">\n          <div [ngClass]=\"lineDiff[0]\" *ngFor=\"let lineDiff of calculatedDiff\">\n            <div class=\"dmp-line-compare-text\">{{lineDiff[3]}}</div>\n          </div>\n        </div>\n      </div>\n    </div>\n  "}]}],"members":{"left":[{"__symbolic":"property","decorators":[{"__symbolic":"call","expression":{"__symbolic":"reference","module":"@angular/core","name":"Input"}}]}],"right":[{"__symbolic":"property","decorators":[{"__symbolic":"call","expression":{"__symbolic":"reference","module":"@angular/core","name":"Input"}}]}],"lineContextSize":[{"__symbolic":"property","decorators":[{"__symbolic":"call","expression":{"__symbolic":"reference","module":"@angular/core","name":"Input"}}]}],"__ctor__":[{"__symbolic":"constructor","parameters":[{"__symbolic":"reference","module":"./diffMatchPatch.service","name":"DiffMatchPatchService"}]}],"ngOnInit":[{"__symbolic":"method"}],"ngOnChanges":[{"__symbolic":"method"}],"updateHtml":[{"__symbolic":"method"}],"calculateLineDiff":[{"__symbolic":"method"}],"outputEqualDiff":[{"__symbolic":"method"}],"outputEqualDiffLines":[{"__symbolic":"method"}],"outputDeleteDiff":[{"__symbolic":"method"}],"outputInsertDiff":[{"__symbolic":"method"}]}}}}]